[
  {
    "date": "2026-02-27T07:58:28.230Z",
    "highRisk": [
      {
        "id": 18,
        "name": "Plagioclase",
        "currentPrice": 42,
        "priceChange": "-38.49",
        "priceChange7d": "1.07",
        "priceChange30d": "16.19",
        "volatility": "26.23",
        "momentum": "16.67",
        "volume": 3536175,
        "volumeCategory": "Very High",
        "investmentScore": "100.0",
        "dataPoints": 421
      },
      {
        "id": 36,
        "name": "Mexallon",
        "currentPrice": 72,
        "priceChange": "-47.35",
        "priceChange7d": "3.77",
        "priceChange30d": "10.51",
        "volatility": "28.15",
        "momentum": "26.06",
        "volume": 599605830,
        "volumeCategory": "Very High",
        "investmentScore": "100.0",
        "dataPoints": 421
      },
      {
        "id": 178,
        "name": "Carbonized Lead S",
        "currentPrice": 3,
        "priceChange": "-74.54",
        "priceChange7d": "-48.13",
        "priceChange30d": "-69.19",
        "volatility": "65.88",
        "momentum": "11.37",
        "volume": 77684,
        "volumeCategory": "Very High",
        "investmentScore": "100.0",
        "dataPoints": 421
      },
      {
        "id": 182,
        "name": "Titanium Sabot S",
        "currentPrice": 10,
        "priceChange": "-7.21",
        "priceChange7d": "-23.72",
        "priceChange30d": "-49.10",
        "volatility": "90.01",
        "momentum": "11.22",
        "volume": 203838,
        "volumeCategory": "Very High",
        "investmentScore": "100.0",
        "dataPoints": 421
      },
      {
        "id": 186,
        "name": "Carbonized Lead M",
        "currentPrice": 14,
        "priceChange": "16.87",
        "priceChange7d": "121.87",
        "priceChange30d": "-5.33",
        "volatility": "51.81",
        "momentum": "25.89",
        "volume": 180180,
        "volumeCategory": "Very High",
        "investmentScore": "100.0",
        "dataPoints": 421
      }
    ],
    "lowRisk": [
      {
        "id": 589,
        "name": "Executioner",
        "currentPrice": 580447,
        "priceChange": "61.84",
        "priceChange7d": "2.34",
        "priceChange30d": "32.38",
        "volatility": "14.78",
        "momentum": "26.18",
        "volume": 47,
        "volumeCategory": "Low",
        "investmentScore": "100.0",
        "dataPoints": 421
      },
      {
        "id": 2327,
        "name": "Microfiber Shielding",
        "currentPrice": 16150,
        "priceChange": "19.45",
        "priceChange7d": "2.41",
        "priceChange30d": "1.00",
        "volatility": "11.26",
        "momentum": "8.32",
        "volume": 221416,
        "volumeCategory": "Very High",
        "investmentScore": "100.0",
        "dataPoints": 421
      },
      {
        "id": 2390,
        "name": "Electrolytes",
        "currentPrice": 603,
        "priceChange": "-6.46",
        "priceChange7d": "-1.55",
        "priceChange30d": "-0.92",
        "volatility": "13.61",
        "momentum": "11.63",
        "volume": 3731837,
        "volumeCategory": "Very High",
        "investmentScore": "100.0",
        "dataPoints": 421
      },
      {
        "id": 2397,
        "name": "Industrial Fibers",
        "currentPrice": 788,
        "priceChange": "-11.35",
        "priceChange7d": "-5.28",
        "priceChange30d": "-2.74",
        "volatility": "14.41",
        "momentum": "16.89",
        "volume": 2771608,
        "volumeCategory": "Very High",
        "investmentScore": "100.0",
        "dataPoints": 421
      },
      {
        "id": 2401,
        "name": "Chiral Structures",
        "currentPrice": 699,
        "priceChange": "-22.98",
        "priceChange7d": "-5.10",
        "priceChange30d": "-6.68",
        "volatility": "14.27",
        "momentum": "17.22",
        "volume": 3240993,
        "volumeCategory": "Very High",
        "investmentScore": "100.0",
        "dataPoints": 421
      }
    ],
    "aiAnalysis": {
      "introParagraph": "The low-risk segment continues to show steady performance with items like Executioner, Microfiber Shielding, Electrolytes. Their consistent volume and low volatility make them solid choices for traders looking to preserve capital.",
      "detailParagraph": "On the high-risk side, keep an eye on Plagioclase at 42 ISK with +16.67% momentum. Volatile picks like these can pay off big if you time your trades right."
    },
    "metadata": {
      "itemsAnalyzed": 9976,
      "itemsFetched": 9977,
      "analysisTime": "189m 41s",
      "timestamp": "2026-02-27T07:58:27.931Z",
      "environment": "GitHub Actions"
    }
  },
  {
    "date": "2026-02-28T07:31:51.403Z",
    "highRisk": [
      {
        "id": 18,
        "name": "Plagioclase",
        "currentPrice": 49,
        "priceChange": "-27.78",
        "priceChange7d": "18.35",
        "priceChange30d": "36.35",
        "volatility": "26.19",
        "momentum": "16.94",
        "volume": 4334634,
        "volumeCategory": "Very High",
        "investmentScore": "100.0",
        "dataPoints": 422
      },
      {
        "id": 36,
        "name": "Mexallon",
        "currentPrice": 75,
        "priceChange": "-44.43",
        "priceChange7d": "11.31",
        "priceChange30d": "6.34",
        "volatility": "28.12",
        "momentum": "25.58",
        "volume": 814843765,
        "volumeCategory": "Very High",
        "investmentScore": "100.0",
        "dataPoints": 422
      },
      {
        "id": 41,
        "name": "Garbage",
        "currentPrice": 95,
        "priceChange": "213.98",
        "priceChange7d": "0.00",
        "priceChange30d": "354.23",
        "volatility": "133.99",
        "momentum": "-2.93",
        "volume": 200296,
        "volumeCategory": "Very High",
        "investmentScore": "100.0",
        "dataPoints": 422
      },
      {
        "id": 43,
        "name": "Antibiotics",
        "currentPrice": 333,
        "priceChange": "9.03",
        "priceChange7d": "119.13",
        "priceChange30d": "132.76",
        "volatility": "16.13",
        "momentum": "9.91",
        "volume": 92804,
        "volumeCategory": "Very High",
        "investmentScore": "100.0",
        "dataPoints": 422
      },
      {
        "id": 182,
        "name": "Titanium Sabot S",
        "currentPrice": 21,
        "priceChange": "89.41",
        "priceChange7d": "54.32",
        "priceChange30d": "3.91",
        "volatility": "89.86",
        "momentum": "12.75",
        "volume": 144610,
        "volumeCategory": "Very High",
        "investmentScore": "100.0",
        "dataPoints": 422
      }
    ],
    "lowRisk": [
      {
        "id": 589,
        "name": "Executioner",
        "currentPrice": 588665,
        "priceChange": "64.13",
        "priceChange7d": "7.73",
        "priceChange30d": "16.34",
        "volatility": "14.77",
        "momentum": "26.94",
        "volume": 79,
        "volumeCategory": "Low",
        "investmentScore": "100.0",
        "dataPoints": 422
      },
      {
        "id": 967,
        "name": "Caldari Shuttle Blueprint",
        "currentPrice": 54686,
        "priceChange": "29.68",
        "priceChange7d": "8.14",
        "priceChange30d": "8.85",
        "volatility": "14.95",
        "momentum": "1.83",
        "volume": 32,
        "volumeCategory": "Low",
        "investmentScore": "100.0",
        "dataPoints": 422
      },
      {
        "id": 2327,
        "name": "Microfiber Shielding",
        "currentPrice": 16500,
        "priceChange": "22.04",
        "priceChange7d": "8.84",
        "priceChange30d": "16.94",
        "volatility": "11.27",
        "momentum": "8.06",
        "volume": 89094,
        "volumeCategory": "Very High",
        "investmentScore": "100.0",
        "dataPoints": 422
      },
      {
        "id": 2390,
        "name": "Electrolytes",
        "currentPrice": 610,
        "priceChange": "-5.46",
        "priceChange7d": "4.52",
        "priceChange30d": "-5.10",
        "volatility": "13.60",
        "momentum": "10.65",
        "volume": 2831666,
        "volumeCategory": "Very High",
        "investmentScore": "100.0",
        "dataPoints": 422
      },
      {
        "id": 2397,
        "name": "Industrial Fibers",
        "currentPrice": 829,
        "priceChange": "-6.79",
        "priceChange7d": "3.56",
        "priceChange30d": "-4.33",
        "volatility": "14.41",
        "momentum": "15.73",
        "volume": 1556387,
        "volumeCategory": "Very High",
        "investmentScore": "100.0",
        "dataPoints": 422
      }
    ],
    "aiAnalysis": {
      "introParagraph": "The low-risk segment continues to show steady performance with items like Executioner, Caldari Shuttle Blueprint, Microfiber Shielding. Their consistent volume and low volatility make them solid choices for traders looking to preserve capital.",
      "detailParagraph": "On the high-risk side, keep an eye on Plagioclase at 49 ISK with +16.94% momentum. Volatile picks like these can pay off big if you time your trades right."
    },
    "metadata": {
      "itemsAnalyzed": 9976,
      "itemsFetched": 9977,
      "analysisTime": "193m 51s",
      "timestamp": "2026-02-28T07:31:51.095Z",
      "environment": "GitHub Actions"
    }
  }
]